log_request_id/__init__.py
log_request_id/filters.py
log_request_id/middleware.py
log_request_id/models.py
log_request_id/session.py
log_request_id/tests.py
log_request_id/__pycache__/__init__.cpython-38.pyc
log_request_id/__pycache__/middleware.cpython-38.pyc
ocp_log_request_id-1.6.0.dist-info/LICENSE
ocp_log_request_id-1.6.0.dist-info/METADATA
ocp_log_request_id-1.6.0.dist-info/WHEEL
ocp_log_request_id-1.6.0.dist-info/top_level.txt
ocp_log_request_id-1.6.0.dist-info/RECORD
